{
  "date": "2026-07-10",
  "entries": [
    {
      "key": "rss:error:microsoft-ai",
      "date": "2026-07-10",
      "source": "rss",
      "level": "error",
      "detail_id": "microsoft-ai",
      "message": "410 Client Error: Gone for url: https://blogs.microsoft.com/ai/feed/",
      "raw": {
        "source_id": "microsoft-ai",
        "error": "410 Client Error: Gone for url: https://blogs.microsoft.com/ai/feed/"
      }
    },
    {
      "key": "wikipedia:error:TikTok",
      "date": "2026-07-10",
      "source": "wikipedia",
      "level": "error",
      "detail_id": "TikTok",
      "message": "404 Client Error: Not Found for url: https://wikimedia.org/api/rest_v1/metrics/pageviews/per-article/en.wikipedia.org/all-access/all-agents/TikTok/daily/20260708/20260708",
      "raw": {
        "title": "TikTok",
        "resolved_title": "TikTok",
        "error": "404 Client Error: Not Found for url: https://wikimedia.org/api/rest_v1/metrics/pageviews/per-article/en.wikipedia.org/all-access/all-agents/TikTok/daily/20260708/20260708"
      }
    },
    {
      "key": "wikipedia:error:Search_engine_optimization",
      "date": "2026-07-10",
      "source": "wikipedia",
      "level": "error",
      "detail_id": "Search_engine_optimization",
      "message": "404 Client Error: Not Found for url: https://wikimedia.org/api/rest_v1/metrics/pageviews/per-article/en.wikipedia.org/all-access/all-agents/Search_engine_optimization/daily/20260708/20260708",
      "raw": {
        "title": "Search_engine_optimization",
        "resolved_title": "Search engine optimization",
        "error": "404 Client Error: Not Found for url: https://wikimedia.org/api/rest_v1/metrics/pageviews/per-article/en.wikipedia.org/all-access/all-agents/Search_engine_optimization/daily/20260708/20260708"
      }
    },
    {
      "key": "wikipedia:warning:Artificial_intelligence",
      "date": "2026-07-10",
      "source": "wikipedia",
      "level": "warning",
      "detail_id": "Artificial_intelligence",
      "message": "404 Client Error: Not Found for url: https://wikimedia.org/api/rest_v1/metrics/pageviews/per-article/en.wikipedia.org/all-access/all-agents/Artificial_intelligence/daily/20260709/20260709",
      "raw": {
        "title": "Artificial_intelligence",
        "observed_date": "2026-07-09",
        "warning": "404 Client Error: Not Found for url: https://wikimedia.org/api/rest_v1/metrics/pageviews/per-article/en.wikipedia.org/all-access/all-agents/Artificial_intelligence/daily/20260709/20260709"
      }
    },
    {
      "key": "wikipedia:warning:TikTok",
      "date": "2026-07-10",
      "source": "wikipedia",
      "level": "warning",
      "detail_id": "TikTok",
      "message": "429 Client Error: Too Many Requests for url: https://en.wikipedia.org/w/api.php?action=query&format=json&formatversion=2&redirects=1&titles=TikTok",
      "raw": {
        "title": "TikTok",
        "warning": "429 Client Error: Too Many Requests for url: https://en.wikipedia.org/w/api.php?action=query&format=json&formatversion=2&redirects=1&titles=TikTok"
      }
    }
  ],
  "summary": {
    "entry_count": 5,
    "by_level": {
      "error": 3,
      "warning": 2
    },
    "by_source": {
      "rss": 1,
      "wikipedia": 4
    },
    "continuous_failures": [
      {
        "key": "rss:error:microsoft-ai",
        "source": "rss",
        "level": "error",
        "detail_id": "microsoft-ai",
        "message": "410 Client Error: Gone for url: https://blogs.microsoft.com/ai/feed/",
        "first_seen": "2026-06-11",
        "last_seen": "2026-07-10",
        "consecutive_days": 30
      }
    ]
  }
}
